hoardy_adb/__init__.py
hoardy_adb/__main__.py
hoardy_adb-2.0.1.dist-info/LICENSE.txt
hoardy_adb-2.0.1.dist-info/METADATA
hoardy_adb-2.0.1.dist-info/WHEEL
hoardy_adb-2.0.1.dist-info/entry_points.txt
hoardy_adb-2.0.1.dist-info/top_level.txt
hoardy_adb-2.0.1.dist-info/RECORD
