Metadata-Version: 2.2
Name: hoardy-adb
Version: 2.0.1
Summary: Backup and restore Android devices, list contents of, unpack, and convert Android Backup files to TAR files and back, decrypt, encrypt, split them into by-app pieces, etc. Android Backup files are `backup.ab`, `*.ab`, `*.adb`, and similarly named files produced by `adb shell bu backup`, `adb backup`, `bmgr`, and similar tools.
Author-email: Jan Malakhovski <oxij@oxij.org>
License: GPL-3.0-or-later
Project-URL: Homepage, https://oxij.org/software/hoardy-adb/
Project-URL: GitHub, https://github.com/Own-Data-Privateer/hoardy-adb
Project-URL: Support Development, https://oxij.org/#support
Keywords: android,backup,android backup,adb,ab,adb backup
Classifier: Development Status :: 4 - Beta
Classifier: Programming Language :: Python :: 3
Classifier: License :: OSI Approved :: GNU General Public License v3 or later (GPLv3+)
Classifier: Intended Audience :: End Users/Desktop
Classifier: Topic :: Security :: Cryptography
Classifier: Topic :: System :: Archiving
Classifier: Topic :: System :: Archiving :: Backup
Classifier: Topic :: System :: Recovery Tools
Classifier: Operating System :: POSIX
Classifier: Environment :: Console
Requires-Python: >=3.11
License-File: LICENSE.txt
Requires-Dist: kisstdlib==0.0.12
Requires-Dist: cryptography
